tinydb_base/__init__.py
tinydb_base/cryptography.py
tinydb_base/data.py
tinydb_base/exceptions.py
tinydb_base/factory.py
tinydb_base/getSet.py
tinydb_base/getSetSercure.py
tinydb_base/output.py
tinydb_base/user.py
tinydb_base/exporter/__init__.py
tinydb_base/exporter/exceptions.py
tinydb_base/exporter/jsonExport.py
tinydb_base/exporter/ymalExport.py
tinydb_baseClass-1.0.0.dist-info/LICENSE.txt
tinydb_baseClass-1.0.0.dist-info/METADATA
tinydb_baseClass-1.0.0.dist-info/WHEEL
tinydb_baseClass-1.0.0.dist-info/top_level.txt
tinydb_baseClass-1.0.0.dist-info/RECORD
