Metadata-Version: 2.1
Name: tinydb-baseClass
Version: 1.0.0
Summary: a base class to tinydb
Home-page: https://github.com/MechaCoder/tinyDbBase
Author: postitnotenija
License: UNKNOWN
Platform: UNKNOWN
Classifier: Programming Language :: Python :: 3
Classifier: Programming Language :: Python :: 3.6
Classifier: Programming Language :: Python :: 3.7
Classifier: Programming Language :: Python :: 3.8
Classifier: License :: OSI Approved :: MIT License
License-File: LICENSE.txt
Requires-Dist: tinydb
Requires-Dist: cryptography (>=3.2)
Requires-Dist: pyyaml
